overhave/__init__.py
overhave/admin/__init__.py
overhave/admin/app.py
overhave/admin/files/ace-src/ace.js
overhave/admin/files/ace-src/mode-gherkin.js
overhave/admin/files/css/overhave.css
overhave/admin/files/favicon.ico
overhave/admin/files/old_logo.ico
overhave/admin/flask/__init__.py
overhave/admin/flask/flask_admin.py
overhave/admin/flask/flask_app.py
overhave/admin/flask/login_manager.py
overhave/admin/templates/draft_detail.html
overhave/admin/templates/emulation.html
overhave/admin/templates/emulation_create.html
overhave/admin/templates/emulation_edit.html
overhave/admin/templates/emulation_run_detail.html
overhave/admin/templates/feature.html
overhave/admin/templates/feature_create.html
overhave/admin/templates/feature_edit.html
overhave/admin/templates/index.html
overhave/admin/templates/login.html
overhave/admin/templates/overhave_master.html
overhave/admin/templates/test_run.html
overhave/admin/templates/test_run_detail.html
overhave/admin/templates/test_run_list.html
overhave/admin/templates/test_user.html
overhave/admin/templates/test_user_create.html
overhave/admin/templates/test_user_edit.html
overhave/admin/views/__init__.py
overhave/admin/views/access.py
overhave/admin/views/base.py
overhave/admin/views/draft.py
overhave/admin/views/emulation.py
overhave/admin/views/emulation_run.py
overhave/admin/views/feature.py
overhave/admin/views/formatters/__init__.py
overhave/admin/views/formatters/formatters.py
overhave/admin/views/formatters/helpers.py
overhave/admin/views/formatters/safe_formatter.py
overhave/admin/views/index/__init__.py
overhave/admin/views/index/custom_page.py
overhave/admin/views/index/login_form.py
overhave/admin/views/index/view.py
overhave/admin/views/scenario_test_run.py
overhave/admin/views/tag.py
overhave/admin/views/testing_users.py
overhave/api/__init__.py
overhave/api/app.py
overhave/api/asgi.py
overhave/api/auth/__init__.py
overhave/api/auth/models.py
overhave/api/auth/regular.py
overhave/api/auth/token.py
overhave-5.2.5.dist-info/METADATA
overhave-5.2.5.dist-info/WHEEL
overhave-5.2.5.dist-info/entry_points.txt
overhave-5.2.5.dist-info/RECORD
