Metadata-Version: 2.3
Name: overhave
Version: 5.2.5
Summary: Overhave - web-framework for BDD
Author: Vladislav Mukhamatnurov
Author-email: livestreamepidemz@yandex.ru
Requires-Python: >=3.11,<3.13
Classifier: Development Status :: 5 - Production/Stable
Classifier: Framework :: Flask
Classifier: Framework :: Pytest
Classifier: Intended Audience :: Developers
Classifier: License :: OSI Approved :: Apache Software License
Classifier: Operating System :: OS Independent
Classifier: Programming Language :: Python :: 3
Classifier: Programming Language :: Python :: 3.11
Classifier: Programming Language :: Python :: 3.12
Classifier: Programming Language :: Python :: 3.10
Classifier: Topic :: Software Development :: Libraries :: Application Frameworks
Classifier: Topic :: Software Development :: Testing
Classifier: Topic :: Software Development :: Testing :: BDD
Requires-Dist: GitPython (>=3.1.15,<4.0.0)
Requires-Dist: WTForms (>=2.2)
Requires-Dist: aiofiles (>=0.8.0,<0.9.0)
Requires-Dist: alembic (>=1.4.3,<2.0.0)
Requires-Dist: boto3 (>=1.17.16,<2.0.0)
Requires-Dist: boto3-type-annotations (>=0.3.1,<0.4.0)
Requires-Dist: fastapi (>=0.99.0)
Requires-Dist: flask (>=2.3.2,<3.0.0)
Requires-Dist: flask-admin (>=1.6.1,<2.0.0)
Requires-Dist: flask-login (>=0.6.2,<0.7.0)
Requires-Dist: flask-wtf (>=1.1.1,<2.0.0)
Requires-Dist: httptools (>=0.6.4,<0.7.0)
Requires-Dist: httpx (>=0.27.0,<0.28.0)
Requires-Dist: ldap3 (>=2.6,<3.0)
Requires-Dist: orjson (>=3.9.10,<4.0.0)
Requires-Dist: prometheus-client (>=0.16.0)
Requires-Dist: psycopg2-binary (>=2.8,<3.0)
Requires-Dist: pydantic (>=1.7)
Requires-Dist: pydantic-settings (>=2.0.1,<3.0.0)
Requires-Dist: python-dateutil (>=2.8.1,<3.0.0)
Requires-Dist: python-gitlab (>=2.9.0,<3.0.0)
Requires-Dist: python-jose (>=3.3.0,<4.0.0)
Requires-Dist: python-ldap (==3.4.3)
Requires-Dist: python-multipart (>=0.0.5,<0.0.6)
Requires-Dist: pytz (>=2020.1,<2021.0)
Requires-Dist: redis (>=5.0.0,<6.0.0)
Requires-Dist: sqlalchemy (>=2.0.17,<3.0.0)
Requires-Dist: sqlalchemy-utc (>=0.14.0,<0.15.0)
Requires-Dist: sqlalchemy-utils (>=0.41.1,<0.42.0)
Requires-Dist: tenacity (>=8.2.3,<9.0.0)
Requires-Dist: typer (>=0.7.0,<0.8.0)
Requires-Dist: walrus (>=0.9.2,<0.10.0)
Requires-Dist: wsgi_intercept (>=1.8,<2.0)
Requires-Dist: yarl (>=1.1.1)
